{
    "assets": [],
    "comments": [],
    "cookTime": null,
    "createdAt": "2024-04-30T00:53:17.648795Z",
    "dateAdded": "2024-04-30",
    "dateUpdated": "2024-04-30T20:24:09.550002Z",
    "description": "",
    "extras": {},
    "groupId": "cb5e8791-b70c-40d4-930c-8b656d0363b6",
    "householdId": "74cd302c-032c-4707-b612-ada7618e0847",
    "id": "ffe8e534-a05b-42de-a833-e05d67c02169",
    "image": null,
    "lastMade": null,
    "name": "Week's Sundries",
    "notes": [],
    "nutrition": {
        "calories": null,
        "carbohydrateContent": null,
        "cholesterolContent": null,
        "fatContent": null,
        "fiberContent": null,
        "proteinContent": null,
        "saturatedFatContent": null,
        "sodiumContent": null,
        "sugarContent": null,
        "transFatContent": null,
        "unsaturatedFatContent": null
    },
    "orgURL": null,
    "performTime": null,
    "prepTime": null,
    "rating": null,
    "recipeCategory": [
        {
            "id": "528184fc-6756-4323-a0c3-ece1c3a4dc9e",
            "name": "shopping",
            "slug": "shopping"
        }
    ],
    "recipeIngredient": [
        {
            "disableAmount": false,
            "display": "2 \u00b9/\u2082 lbs grapes",
            "food": {
                "aliases": [],
                "createdAt": "2024-04-30T20:20:38.430985Z",
                "description": "",
                "extras": {},
                "id": "e8b93746-8843-4547-a6c3-0911d1f9c48e",
                "label": {
                    "color": "#a7d766",
                    "groupId": "cb5e8791-b70c-40d4-930c-8b656d0363b6",
                    "id": "e5ad61bd-8357-4ca3-bd44-a0bbf83bd560",
                    "name": "Produce"
                },
                "labelId": "e5ad61bd-8357-4ca3-bd44-a0bbf83bd560",
                "name": "grapes",
                "onHand": false,
                "pluralName": null,
                "updatedAt": "2024-04-30T20:26:03.942227Z"
            },
            "isFood": true,
            "note": "",
            "originalText": "2.5 lbs bag grapes",
            "quantity": 2.5,
            "referenceId": "db677ef8-a52e-46c7-97e5-6fca0290a9a7",
            "title": "",
            "unit": {
                "abbreviation": "lb",
                "aliases": [],
                "createdAt": "2024-04-26T19:32:10.726674Z",
                "description": "",
                "extras": {},
                "fraction": true,
                "id": "99f4d2e1-d11e-4746-a48b-9a96d8452450",
                "name": "pound",
                "onHand": false,
                "pluralAbbreviation": "lbs",
                "pluralName": "pounds",
                "updatedAt": "2024-05-02T12:28:24.776546Z",
                "useAbbreviation": true
            }
        },
        {
            "disableAmount": false,
            "display": "1 lb carrot",
            "food": {
                "aliases": [],
                "createdAt": "2024-04-26T19:32:36.805146Z",
                "description": "",
                "extras": {},
                "id": "a22ede96-a507-486e-89f5-fc2184062be4",
                "label": {
                    "color": "#a7d766",
                    "groupId": "cb5e8791-b70c-40d4-930c-8b656d0363b6",
                    "id": "e5ad61bd-8357-4ca3-bd44-a0bbf83bd560",
                    "name": "Produce"
                },
                "labelId": "e5ad61bd-8357-4ca3-bd44-a0bbf83bd560",
                "name": "carrot",
                "onHand": false,
                "pluralName": null,
                "updatedAt": "2024-04-27T03:14:32.053074Z"
            },
            "isFood": true,
            "note": "",
            "originalText": "16.0 ounce carrots",
            "quantity": 1.0,
            "referenceId": "fa7f9e04-9d9f-4e52-b8a8-818cab49beed",
            "title": "",
            "unit": {
                "abbreviation": "lb",
                "aliases": [],
                "createdAt": "2024-04-26T19:32:10.726674Z",
                "description": "",
                "extras": {},
                "fraction": true,
                "id": "99f4d2e1-d11e-4746-a48b-9a96d8452450",
                "name": "pound",
                "onHand": false,
                "pluralAbbreviation": "lbs",
                "pluralName": "pounds",
                "updatedAt": "2024-05-02T12:28:24.776546Z",
                "useAbbreviation": true
            }
        },
        {
            "disableAmount": false,
            "display": "1 jar pickles",
            "food": {
                "aliases": [],
                "createdAt": "2024-04-27T12:27:52.977982Z",
                "description": "",
                "extras": {},
                "id": "daa73cf2-7063-448a-a16a-f900a12d9856",
                "label": {
                    "color": "#5c57b0",
                    "groupId": "cb5e8791-b70c-40d4-930c-8b656d0363b6",
                    "id": "a4d1d7d5-d2c2-4c03-8eec-f43d20b27467",
                    "name": "Cans and Jars"
                },
                "labelId": "a4d1d7d5-d2c2-4c03-8eec-f43d20b27467",
                "name": "pickles",
                "onHand": false,
                "pluralName": null,
                "updatedAt": "2024-04-27T12:30:33.097609Z"
            },
            "isFood": true,
            "note": "",
            "originalText": "16.0 ounce pickles",
            "quantity": 1.0,
            "referenceId": "cf9b3a32-cadd-4928-adea-794f93e7c9d5",
            "title": "",
            "unit": {
                "abbreviation": "",
                "aliases": [],
                "createdAt": "2024-04-30T20:18:45.180773Z",
                "description": "",
                "extras": {},
                "fraction": true,
                "id": "ef4fa795-bd9c-46ef-81bd-65a57e906fe1",
                "name": "jar",
                "onHand": false,
                "pluralAbbreviation": "",
                "pluralName": "jars",
                "updatedAt": "2024-05-13T12:24:37.051214Z",
                "useAbbreviation": false
            }
        },
        {
            "disableAmount": false,
            "display": "8 lbs oranges",
            "food": {
                "aliases": [],
                "createdAt": "2024-04-26T19:32:57.501061Z",
                "description": "",
                "extras": {},
                "id": "8014c894-5d75-4d79-a7d2-4b715d98926d",
                "label": {
                    "color": "#a7d766",
                    "groupId": "cb5e8791-b70c-40d4-930c-8b656d0363b6",
                    "id": "e5ad61bd-8357-4ca3-bd44-a0bbf83bd560",
                    "name": "Produce"
                },
                "labelId": "e5ad61bd-8357-4ca3-bd44-a0bbf83bd560",
                "name": "oranges",
                "onHand": false,
                "pluralName": null,
                "updatedAt": "2024-04-27T03:06:04.190695Z"
            },
            "isFood": true,
            "note": "",
            "originalText": "8.0 lbs oranges",
            "quantity": 8.0,
            "referenceId": "56c78b67-91e0-46a2-bd94-f0723930fee8",
            "title": "",
            "unit": {
                "abbreviation": "lb",
                "aliases": [],
                "createdAt": "2024-04-26T19:32:10.726674Z",
                "description": "",
                "extras": {},
                "fraction": true,
                "id": "99f4d2e1-d11e-4746-a48b-9a96d8452450",
                "name": "pound",
                "onHand": false,
                "pluralAbbreviation": "lbs",
                "pluralName": "pounds",
                "updatedAt": "2024-05-02T12:28:24.776546Z",
                "useAbbreviation": true
            }
        },
        {
            "disableAmount": false,
            "display": "1 romaine lettuce",
            "food": {
                "aliases": [],
                "createdAt": "2024-04-30T20:21:41.735975Z",
                "description": "",
                "extras": {},
                "id": "9e38ee9e-fed0-40fb-950b-d44c8a56f3b2",
                "label": {
                    "color": "#a7d766",
                    "groupId": "cb5e8791-b70c-40d4-930c-8b656d0363b6",
                    "id": "e5ad61bd-8357-4ca3-bd44-a0bbf83bd560",
                    "name": "Produce"
                },
                "labelId": "e5ad61bd-8357-4ca3-bd44-a0bbf83bd560",
                "name": "romaine lettuce",
                "onHand": false,
                "pluralName": null,
                "updatedAt": "2024-04-30T20:25:56.504196Z"
            },
            "isFood": true,
            "note": "",
            "originalText": "1.0 romaine lettuce",
            "quantity": 1.0,
            "referenceId": "8402750f-9954-4da4-bcb7-c24cbc5b0101",
            "title": "",
            "unit": null
        },
        {
            "disableAmount": false,
            "display": "1 red pepper",
            "food": {
                "aliases": [],
                "createdAt": "2024-04-29T23:56:11.556967Z",
                "description": "",
                "extras": {},
                "id": "5fc2dc18-46db-4b96-9680-6484a76b9093",
                "label": {
                    "color": "#a7d766",
                    "groupId": "cb5e8791-b70c-40d4-930c-8b656d0363b6",
                    "id": "e5ad61bd-8357-4ca3-bd44-a0bbf83bd560",
                    "name": "Produce"
                },
                "labelId": "e5ad61bd-8357-4ca3-bd44-a0bbf83bd560",
                "name": "red pepper",
                "onHand": false,
                "pluralName": null,
                "updatedAt": "2024-04-30T00:03:47.195518Z"
            },
            "isFood": true,
            "note": "",
            "originalText": "1.0 red pepper",
            "quantity": 1.0,
            "referenceId": "154fe6ba-9f39-48f7-90ac-a9d7d5425b1e",
            "title": "",
            "unit": null
        },
        {
            "disableAmount": false,
            "display": "1 cucumber",
            "food": {
                "aliases": [],
                "createdAt": "2024-04-26T19:32:17.899950Z",
                "description": "",
                "extras": {},
                "id": "4b1a5dc8-edfb-4882-aae4-819bc1122cb3",
                "label": {
                    "color": "#a7d766",
                    "groupId": "cb5e8791-b70c-40d4-930c-8b656d0363b6",
                    "id": "e5ad61bd-8357-4ca3-bd44-a0bbf83bd560",
                    "name": "Produce"
                },
                "labelId": "e5ad61bd-8357-4ca3-bd44-a0bbf83bd560",
                "name": "cucumber",
                "onHand": false,
                "pluralName": null,
                "updatedAt": "2024-04-30T02:04:46.686427Z"
            },
            "isFood": true,
            "note": "",
            "originalText": "1.0 cucumber",
            "quantity": 1.0,
            "referenceId": "d230978c-2dc8-4b52-ab49-4c7ee664699a",
            "title": "",
            "unit": null
        },
        {
            "disableAmount": false,
            "display": "2 tomato",
            "food": {
                "aliases": [],
                "createdAt": "2024-04-26T19:32:18.483079Z",
                "description": "",
                "extras": {},
                "id": "69622eea-3935-4d27-91a8-d1f30ac20746",
                "label": {
                    "color": "#a7d766",
                    "groupId": "cb5e8791-b70c-40d4-930c-8b656d0363b6",
                    "id": "e5ad61bd-8357-4ca3-bd44-a0bbf83bd560",
                    "name": "Produce"
                },
                "labelId": "e5ad61bd-8357-4ca3-bd44-a0bbf83bd560",
                "name": "tomato ",
                "onHand": false,
                "pluralName": null,
                "updatedAt": "2024-04-27T03:19:35.365817Z"
            },
            "isFood": true,
            "note": "",
            "originalText": "2.0 plum tomatoes",
            "quantity": 2.0,
            "referenceId": "e356b434-4d4f-4cb1-a157-f3979f1242e2",
            "title": "",
            "unit": null
        },
        {
            "disableAmount": false,
            "display": "1 bunch celery",
            "food": {
                "aliases": [],
                "createdAt": "2024-04-26T19:32:50.103022Z",
                "description": "",
                "extras": {},
                "id": "93acbbe9-3ea9-4f6e-aae1-06c116126b32",
                "label": {
                    "color": "#a7d766",
                    "groupId": "cb5e8791-b70c-40d4-930c-8b656d0363b6",
                    "id": "e5ad61bd-8357-4ca3-bd44-a0bbf83bd560",
                    "name": "Produce"
                },
                "labelId": "e5ad61bd-8357-4ca3-bd44-a0bbf83bd560",
                "name": "celery",
                "onHand": false,
                "pluralName": null,
                "updatedAt": "2024-04-27T03:07:16.816049Z"
            },
            "isFood": true,
            "note": "",
            "originalText": "none celery",
            "quantity": 1.0,
            "referenceId": "89ac414e-8cb8-46e8-b94e-31338b00a060",
            "title": "",
            "unit": {
                "abbreviation": "",
                "aliases": [],
                "createdAt": "2024-04-27T11:42:55.765925Z",
                "description": "",
                "extras": {},
                "fraction": true,
                "id": "195e7e83-0195-40e4-815e-6c7cd47ac3a9",
                "name": "bunch",
                "onHand": false,
                "pluralAbbreviation": "",
                "pluralName": "bunches",
                "updatedAt": "2024-05-13T12:25:21.687410Z",
                "useAbbreviation": false
            }
        },
        {
            "disableAmount": false,
            "display": "mixed fruit",
            "food": {
                "aliases": [],
                "createdAt": "2024-04-30T20:22:25.910456Z",
                "description": "",
                "extras": {},
                "id": "e4f6ccd4-7314-462a-b8e3-e2e963665057",
                "label": {
                    "color": "#a7d766",
                    "groupId": "cb5e8791-b70c-40d4-930c-8b656d0363b6",
                    "id": "e5ad61bd-8357-4ca3-bd44-a0bbf83bd560",
                    "name": "Produce"
                },
                "labelId": "e5ad61bd-8357-4ca3-bd44-a0bbf83bd560",
                "name": "mixed fruit",
                "onHand": false,
                "pluralName": null,
                "updatedAt": "2024-04-30T20:25:42.136886Z"
            },
            "isFood": true,
            "note": "",
            "originalText": "none mixed fruit",
            "quantity": 0.0,
            "referenceId": "40fcbcd3-f2bf-463a-9a2f-24668f7fb079",
            "title": "",
            "unit": null
        },
        {
            "disableAmount": false,
            "display": "berries",
            "food": {
                "aliases": [],
                "createdAt": "2024-04-30T20:22:37.839565Z",
                "description": "",
                "extras": {},
                "id": "e2a6326a-90c7-4c66-a8ed-1740f51872a9",
                "label": {
                    "color": "#a7d766",
                    "groupId": "cb5e8791-b70c-40d4-930c-8b656d0363b6",
                    "id": "e5ad61bd-8357-4ca3-bd44-a0bbf83bd560",
                    "name": "Produce"
                },
                "labelId": "e5ad61bd-8357-4ca3-bd44-a0bbf83bd560",
                "name": "berries",
                "onHand": false,
                "pluralName": null,
                "updatedAt": "2024-04-30T20:25:31.242259Z"
            },
            "isFood": true,
            "note": "",
            "originalText": "none berries",
            "quantity": 0.0,
            "referenceId": "0913d428-1cd7-4f8c-ac83-52c86ece5eaf",
            "title": "",
            "unit": null
        },
        {
            "disableAmount": false,
            "display": "1 bag turkey pepperoni",
            "food": {
                "aliases": [],
                "createdAt": "2024-04-30T20:23:00.696281Z",
                "description": "",
                "extras": {},
                "id": "0420a619-3c02-455e-86aa-2b1731d61458",
                "label": {
                    "color": "#5c57b0",
                    "groupId": "cb5e8791-b70c-40d4-930c-8b656d0363b6",
                    "id": "a4d1d7d5-d2c2-4c03-8eec-f43d20b27467",
                    "name": "Cans and Jars"
                },
                "labelId": "a4d1d7d5-d2c2-4c03-8eec-f43d20b27467",
                "name": "turkey pepperoni",
                "onHand": false,
                "pluralName": null,
                "updatedAt": "2024-04-30T20:25:20.540594Z"
            },
            "isFood": true,
            "note": "",
            "originalText": "none turkey pepperoni",
            "quantity": 1.0,
            "referenceId": "3a24d6fb-434f-4abd-9f66-f4cd415754a0",
            "title": "",
            "unit": {
                "abbreviation": "",
                "aliases": [],
                "createdAt": "2024-04-27T02:34:36.952058Z",
                "description": "",
                "extras": {},
                "fraction": true,
                "id": "237f6be2-5e4b-4583-8e04-c9e298c3ac21",
                "name": "bag",
                "onHand": false,
                "pluralAbbreviation": "",
                "pluralName": "bags",
                "updatedAt": "2024-05-13T12:25:27.496645Z",
                "useAbbreviation": false
            }
        },
        {
            "disableAmount": false,
            "display": "1 bag croutons",
            "food": {
                "aliases": [],
                "createdAt": "2024-04-27T12:27:48.651524Z",
                "description": "",
                "extras": {},
                "id": "8c36eb30-421f-4bce-8c15-515053a32c47",
                "label": {
                    "color": "#5c57b0",
                    "groupId": "cb5e8791-b70c-40d4-930c-8b656d0363b6",
                    "id": "a4d1d7d5-d2c2-4c03-8eec-f43d20b27467",
                    "name": "Cans and Jars"
                },
                "labelId": "a4d1d7d5-d2c2-4c03-8eec-f43d20b27467",
                "name": "croutons",
                "onHand": false,
                "pluralName": null,
                "updatedAt": "2024-04-27T12:29:50.877239Z"
            },
            "isFood": true,
            "note": "",
            "originalText": "none croutons",
            "quantity": 1.0,
            "referenceId": "fff52c20-c431-4593-8880-dcc6ce0b5c63",
            "title": "",
            "unit": {
                "abbreviation": "",
                "aliases": [],
                "createdAt": "2024-04-27T02:34:36.952058Z",
                "description": "",
                "extras": {},
                "fraction": true,
                "id": "237f6be2-5e4b-4583-8e04-c9e298c3ac21",
                "name": "bag",
                "onHand": false,
                "pluralAbbreviation": "",
                "pluralName": "bags",
                "updatedAt": "2024-05-13T12:25:27.496645Z",
                "useAbbreviation": false
            }
        },
        {
            "disableAmount": false,
            "display": "1 bag goldfish",
            "food": {
                "aliases": [],
                "createdAt": "2024-04-27T12:28:26.381843Z",
                "description": "",
                "extras": {},
                "id": "5d3f61f6-fd77-47a7-8742-57894c85a640",
                "label": {
                    "color": "#5c57b0",
                    "groupId": "cb5e8791-b70c-40d4-930c-8b656d0363b6",
                    "id": "a4d1d7d5-d2c2-4c03-8eec-f43d20b27467",
                    "name": "Cans and Jars"
                },
                "labelId": "a4d1d7d5-d2c2-4c03-8eec-f43d20b27467",
                "name": "goldfish",
                "onHand": false,
                "pluralName": null,
                "updatedAt": "2024-04-27T12:31:39.888480Z"
            },
            "isFood": true,
            "note": "",
            "originalText": "none goldfish",
            "quantity": 1.0,
            "referenceId": "b9923eb9-66c1-413f-8b85-7602d32fe414",
            "title": "",
            "unit": {
                "abbreviation": "",
                "aliases": [],
                "createdAt": "2024-04-27T02:34:36.952058Z",
                "description": "",
                "extras": {},
                "fraction": true,
                "id": "237f6be2-5e4b-4583-8e04-c9e298c3ac21",
                "name": "bag",
                "onHand": false,
                "pluralAbbreviation": "",
                "pluralName": "bags",
                "updatedAt": "2024-05-13T12:25:27.496645Z",
                "useAbbreviation": false
            }
        },
        {
            "disableAmount": false,
            "display": "1 box cheerios",
            "food": {
                "aliases": [],
                "createdAt": "2024-04-27T12:28:40.282111Z",
                "description": "",
                "extras": {},
                "id": "c51beb32-de4d-4852-a165-f8dcc011671b",
                "label": {
                    "color": "#5c57b0",
                    "groupId": "cb5e8791-b70c-40d4-930c-8b656d0363b6",
                    "id": "a4d1d7d5-d2c2-4c03-8eec-f43d20b27467",
                    "name": "Cans and Jars"
                },
                "labelId": "a4d1d7d5-d2c2-4c03-8eec-f43d20b27467",
                "name": "cheerios",
                "onHand": false,
                "pluralName": null,
                "updatedAt": "2024-04-27T12:32:13.016948Z"
            },
            "isFood": true,
            "note": "",
            "originalText": "none cheerios",
            "quantity": 1.0,
            "referenceId": "86de0810-4ce1-45b2-bdbd-b091dbeb0144",
            "title": "",
            "unit": {
                "abbreviation": "",
                "aliases": [],
                "createdAt": "2024-04-30T12:39:03.991880Z",
                "description": "",
                "extras": {},
                "fraction": true,
                "id": "79cee2b6-a596-4e19-8558-8b4eac7c0612",
                "name": "box",
                "onHand": false,
                "pluralAbbreviation": "",
                "pluralName": "boxes",
                "updatedAt": "2024-05-13T12:24:46.180246Z",
                "useAbbreviation": false
            }
        }
    ],
    "recipeInstructions": [
        {
            "id": "e665b04a-d32c-4d99-a12d-d263ce694fae",
            "ingredientReferences": [],
            "summary": null,
            "text": "Put things in grocery bag, pay for them, bring them home. ",
            "title": ""
        }
    ],
    "recipeYield": null,
    "settings": {
        "disableAmount": false,
        "disableComments": false,
        "landscapeView": false,
        "locked": false,
        "public": true,
        "showAssets": false,
        "showNutrition": false
    },
    "slug": "week-s-sundries",
    "tags": [
        {
            "id": "e1c1c1a2-7783-4dc2-979e-a6f35e1c17e9",
            "name": "Needs Pic",
            "slug": "needs-pic"
        }
    ],
    "tools": [],
    "totalTime": null,
    "updatedAt": "2024-04-30T20:24:09.552359Z",
    "userId": "e1703969-a8bc-4ba4-97b8-878de4769c31"
}